src/__init__.py
src/configs.py
src/constants.py
src/conversation.py
src/fm_score.py
src/logging_config.py
src/managed_inference.py
src/prompt_formatter.py
src/replica_manager.py
src/score.py
src/utils.py
src/engine/__init__.py
src/engine/engine.py
src/engine/mii_engine.py
src/engine/mii_engine_v2.py
src/engine/vllm_engine.py
fm_optimized_inference-0.1.dist-info/LICENSE
fm_optimized_inference-0.1.dist-info/METADATA
fm_optimized_inference-0.1.dist-info/WHEEL
fm_optimized_inference-0.1.dist-info/top_level.txt
fm_optimized_inference-0.1.dist-info/RECORD
