Metadata-Version: 2.1
Name: fm-optimized-inference
Version: 0.1
Home-page: 
Author: Microsoft
Author-email: 
Classifier: Development Status :: 3 - Alpha
Classifier: Intended Audience :: Developers
Classifier: License :: OSI Approved :: MIT License
Classifier: Programming Language :: Python :: 3.8
Requires-Python: >=3.8
License-File: LICENSE
Requires-Dist: deepspeed ==0.12.3
Requires-Dist: deepspeed-mii ==0.1.1
Requires-Dist: deepspeed-kernels ==0.0.1.dev1698255861
Requires-Dist: pandas ~=2.1.3
Requires-Dist: transformers ~=4.35.0
Requires-Dist: vllm ==0.2.1.post1
Requires-Dist: aiolimiter ~=1.1.0
Requires-Dist: azure-ai-contentsafety ~=1.0.0b1
Requires-Dist: azure-ai-ml ==1.10.1
Requires-Dist: azure-identity ==1.14.0
Requires-Dist: azureml-ai-monitoring ==0.1.0b4
Requires-Dist: azureml-inference-server-http
Requires-Dist: azureml-mlflow
Requires-Dist: cryptography ~=41.0.5
Requires-Dist: certifi ==2023.07.22
Requires-Dist: requests ~=2.31.0
Requires-Dist: aiohttp ~=3.8.6
Provides-Extra: dev
Requires-Dist: pytest ; extra == 'dev'
